flowdec/__init__.py
flowdec/data.py
flowdec/exec.py
flowdec/fft_pad_rainbow.py
flowdec/fft_utils_np.py
flowdec/fft_utils_test.py
flowdec/fft_utils_tf.py
flowdec/psf.py
flowdec/psf_test.py
flowdec/restoration.py
flowdec/restoration_test.py
flowdec/test_utils.py
flowdec/tf_ops.py
flowdec/tf_ops_test.py
flowdec/validation.py
flowdec/cmd/__init__.py
flowdec/cmd/deconvolution.py
flowdec/datasets/bars-25pct/actual.tif
flowdec/datasets/bars-25pct/data.tif
flowdec/datasets/bars-25pct/kernel.tif
flowdec/datasets/bead-25pct/data.tif
flowdec/datasets/bead-25pct/kernel.tif
flowdec/datasets/neuron-25pct/data.tif
flowdec/datasets/psfs/psfgen1.tif
flowdec/nb/__init__.py
flowdec/nb/logging.py
flowdec/nb/utils.py
flowdec-1.1.0.dist-info/METADATA
flowdec-1.1.0.dist-info/WHEEL
flowdec-1.1.0.dist-info/entry_points.txt
flowdec-1.1.0.dist-info/top_level.txt
flowdec-1.1.0.dist-info/RECORD
