Metadata-Version: 2.1
Name: flowdec
Version: 1.1.0
Summary: TensorFlow Implementations of Signal Deconvolution Algorithms
Home-page: https://github.com/hammerlab/flowdec
Author: Eric Czech
Author-email: eric@hammerlab.org
License: http://www.apache.org/licenses/LICENSE-2.0.html
Platform: UNKNOWN
Classifier: Environment :: Console
Classifier: Operating System :: OS Independent
Classifier: Intended Audience :: Science/Research
Classifier: Topic :: Scientific/Engineering :: Bio-Informatics
Classifier: License :: OSI Approved :: Apache Software License
Classifier: Programming Language :: Python :: 3.6
Requires-Dist: scikit-image (>=0.16.1)
Requires-Dist: matplotlib
Requires-Dist: requests
Provides-Extra: tf
Requires-Dist: tensorflow (>=1.14.0) ; extra == 'tf'
Provides-Extra: tf_gpu
Requires-Dist: tensorflow-gpu (>=1.14.0) ; extra == 'tf_gpu'
